gp_hashing/__init__.py
gp_hashing/generateHash.py
gp_hashing-1.0.4.dist-info/LICENSE
gp_hashing-1.0.4.dist-info/METADATA
gp_hashing-1.0.4.dist-info/WHEEL
gp_hashing-1.0.4.dist-info/top_level.txt
gp_hashing-1.0.4.dist-info/RECORD
