Metadata-Version: 2.1
Name: gp-hashing
Version: 1.0.4
Summary: Generate Hashed Strings Easily.
Home-page: UNKNOWN
Author: Sayak Mukhopadhyay & Shouvik Bajpayee
Author-email: <bajpayeeshouvik@gmail.com>
License: UNKNOWN
Keywords: python,hashing,gp-hashing,generate hash,easy hashing
Platform: UNKNOWN
Classifier: Intended Audience :: Developers
Classifier: Programming Language :: Python :: 3
Classifier: Operating System :: Unix
Classifier: Operating System :: MacOS :: MacOS X
Classifier: Operating System :: Microsoft :: Windows
